{
  "fire_metadata": {
    "name": "Creek_Fire_2020",
    "location": {
      "bbox": [
        -119.65,
        36.85,
        -118.95,
        37.7
      ],
      "center": [
        -119.3,
        37.28
      ],
      "state": "CA"
    },
    "temporal_extent": {
      "ignition_date": "2020-09-04",
      "containment_date": "2020-12-24",
      "pre_fire_monitoring_start": "2020-06-01",
      "post_fire_monitoring_end": "2021-06-01"
    },
    "official_size_acres": 379895
  },
  "simulation_parameters": {
    "grid_resolution_meters": 30,
    "time_step_hours": 1,
    "simulation_duration_hours": 2664,
    "ignition_points": [
      [
        -119.3,
        37.28
      ]
    ],
    "weather_update_frequency_hours": 3
  },
  "data_sources": {
    "satellite_imagery": [
      "Sentinel-2 (10m resolution)",
      "Landsat 8/9 (30m resolution)",
      "MODIS (250m-1km resolution)"
    ],
    "weather_data": [
      "ERA5 Reanalysis (25km resolution)",
      "Fire Weather Index calculations"
    ],
    "topography": [
      "SRTM DEM (30m resolution)",
      "Terrain derivatives (slope, aspect, TWI, TRI)"
    ],
    "fuel_models": [
      "LANDFIRE Surface Fuel Models",
      "LANDFIRE Canopy Characteristics",
      "MODIS Vegetation Indices"
    ],
    "fire_detection": [
      "NASA FIRMS Active Fire Data",
      "MODIS Fire Products",
      "Burned Area Mapping"
    ]
  },
  "validation_metrics": {
    "spatial_accuracy": "Burned area comparison",
    "temporal_accuracy": "Fire progression timing",
    "fire_behavior": "Rate of spread validation"
  }
}